<?xml version="1.0" encoding="UTF-8" standalone="yes"?>
<unit xmlns="http://www.srcML.org/srcML/src" xmlns:cpp="http://www.srcML.org/srcML/cpp" revision="1.0.0" language="C" filename="D:\Pesquisa\Projects\obs-analysis\_cppstats\obs-studio\deps\w32-pthreads\pthread_equal.c"><cpp:include>#<cpp:directive>include</cpp:directive> <cpp:file>"pthread.h"</cpp:file></cpp:include>

<cpp:include>#<cpp:directive>include</cpp:directive> <cpp:file>"implement.h"</cpp:file></cpp:include>

<function><type><name>int</name></type>

<name>pthread_equal</name> <parameter_list>(<parameter><decl><type><name>pthread_t</name></type> <name>t1</name></decl></parameter>, <parameter><decl><type><name>pthread_t</name></type> <name>t2</name></decl></parameter>)</parameter_list>

<block>{<block_content>

<decl_stmt><decl><type><name>int</name></type> <name>result</name></decl>;</decl_stmt>

<expr_stmt><expr><name>result</name> <operator>=</operator> <operator>(</operator> <name><name>t1</name><operator>.</operator><name>p</name></name> <operator>==</operator> <name><name>t2</name><operator>.</operator><name>p</name></name> <operator>&amp;&amp;</operator> <name><name>t1</name><operator>.</operator><name>x</name></name> <operator>==</operator> <name><name>t2</name><operator>.</operator><name>x</name></name> <operator>)</operator></expr>;</expr_stmt>

<return>return <expr><operator>(</operator><name>result</name><operator>)</operator></expr>;</return>

</block_content>}</block></function> 

</unit>
