<?xml version="1.0" encoding="UTF-8" standalone="yes"?>
<unit xmlns="http://www.srcML.org/srcML/src" xmlns:cpp="http://www.srcML.org/srcML/cpp" revision="1.0.0" language="C" filename="D:\Pesquisa\Projects\vlc-analysis\_cppstats_featurelocations\vlc\modules\access\http\resource.h">



















<cpp:if>#<cpp:directive>if</cpp:directive> <expr><operator>!</operator><call><name>defined</name><argument_list>(<argument><expr><name>VLC_HTTP_RESOURCE_H</name></expr></argument>)</argument_list></call></expr></cpp:if>
<cpp:define>#<cpp:directive>define</cpp:directive> <cpp:macro><name>VLC_HTTP_RESOURCE_H</name></cpp:macro> <cpp:value>1</cpp:value></cpp:define>








<struct_decl>struct <name>vlc_http_msg</name>;</struct_decl>
<struct_decl>struct <name>vlc_http_mgr</name>;</struct_decl>
<struct_decl>struct <name>vlc_http_resource</name>;</struct_decl>

<struct>struct <name>vlc_http_resource_cbs</name>
<block>{
<function_decl><type><name>int</name></type> (<modifier>*</modifier><name>request_format</name>)<parameter_list>(<parameter><decl><type><specifier>const</specifier> <name><name>struct</name> <name>vlc_http_resource</name></name> <modifier>*</modifier></type></decl></parameter>,
<parameter><decl><type><name><name>struct</name> <name>vlc_http_msg</name></name> <modifier>*</modifier></type></decl></parameter>, <parameter><decl><type><name>void</name> <modifier>*</modifier></type></decl></parameter>)</parameter_list>;</function_decl>
<function_decl><type><name>int</name></type> (<modifier>*</modifier><name>response_validate</name>)<parameter_list>(<parameter><decl><type><specifier>const</specifier> <name><name>struct</name> <name>vlc_http_resource</name></name> <modifier>*</modifier></type></decl></parameter>,
<parameter><decl><type><specifier>const</specifier> <name><name>struct</name> <name>vlc_http_msg</name></name> <modifier>*</modifier></type></decl></parameter>, <parameter><decl><type><name>void</name> <modifier>*</modifier></type></decl></parameter>)</parameter_list>;</function_decl>
}</block>;</struct>

<struct>struct <name>vlc_http_resource</name>
<block>{
<decl_stmt><decl><type><specifier>const</specifier> <name><name>struct</name> <name>vlc_http_resource_cbs</name></name> <modifier>*</modifier></type><name>cbs</name></decl>;</decl_stmt>
<decl_stmt><decl><type><name><name>struct</name> <name>vlc_http_msg</name></name> <modifier>*</modifier></type><name>response</name></decl>;</decl_stmt>
<decl_stmt><decl><type><name><name>struct</name> <name>vlc_http_mgr</name></name> <modifier>*</modifier></type><name>manager</name></decl>;</decl_stmt>
<decl_stmt><decl><type><name>bool</name></type> <name>secure</name></decl>;</decl_stmt>
<decl_stmt><decl><type><name>bool</name></type> <name>negotiate</name></decl>;</decl_stmt>
<decl_stmt><decl><type><name>bool</name></type> <name>failure</name></decl>;</decl_stmt>
<decl_stmt><decl><type><name>char</name> <modifier>*</modifier></type><name>host</name></decl>;</decl_stmt>
<decl_stmt><decl><type><name>unsigned</name></type> <name>port</name></decl>;</decl_stmt>
<decl_stmt><decl><type><name>char</name> <modifier>*</modifier></type><name>authority</name></decl>;</decl_stmt>
<decl_stmt><decl><type><name>char</name> <modifier>*</modifier></type><name>path</name></decl>;</decl_stmt>
<decl_stmt><decl><type><name>char</name> <modifier>*</modifier></type><name>username</name></decl>;</decl_stmt>
<decl_stmt><decl><type><name>char</name> <modifier>*</modifier></type><name>password</name></decl>;</decl_stmt>
<decl_stmt><decl><type><name>char</name> <modifier>*</modifier></type><name>agent</name></decl>;</decl_stmt>
<decl_stmt><decl><type><name>char</name> <modifier>*</modifier></type><name>referrer</name></decl>;</decl_stmt>
}</block>;</struct>

<function_decl><type><name>int</name></type> <name>vlc_http_res_init</name><parameter_list>(<parameter><decl><type><name><name>struct</name> <name>vlc_http_resource</name></name> <modifier>*</modifier></type></decl></parameter>,
<parameter><decl><type><specifier>const</specifier> <name><name>struct</name> <name>vlc_http_resource_cbs</name></name> <modifier>*</modifier></type><name>cbs</name></decl></parameter>,
<parameter><decl><type><name><name>struct</name> <name>vlc_http_mgr</name></name> <modifier>*</modifier></type><name>mgr</name></decl></parameter>,
<parameter><decl><type><specifier>const</specifier> <name>char</name> <modifier>*</modifier></type><name>uri</name></decl></parameter>, <parameter><decl><type><specifier>const</specifier> <name>char</name> <modifier>*</modifier></type><name>ua</name></decl></parameter>, <parameter><decl><type><specifier>const</specifier> <name>char</name> <modifier>*</modifier></type><name>ref</name></decl></parameter>)</parameter_list>;</function_decl>







<function_decl><type><name>void</name></type> <name>vlc_http_res_destroy</name><parameter_list>(<parameter><decl><type><name><name>struct</name> <name>vlc_http_resource</name></name> <modifier>*</modifier></type></decl></parameter>)</parameter_list>;</function_decl>

<function_decl><type><name><name>struct</name> <name>vlc_http_msg</name></name> <modifier>*</modifier></type><name>vlc_http_res_open</name><parameter_list>(<parameter><decl><type><name><name>struct</name> <name>vlc_http_resource</name></name> <modifier>*</modifier></type><name>res</name></decl></parameter>, <parameter><decl><type><name>void</name> <modifier>*</modifier></type></decl></parameter>)</parameter_list>;</function_decl>
<function_decl><type><name>int</name></type> <name>vlc_http_res_get_status</name><parameter_list>(<parameter><decl><type><name><name>struct</name> <name>vlc_http_resource</name></name> <modifier>*</modifier></type><name>res</name></decl></parameter>)</parameter_list>;</function_decl>









<function_decl><type><name>char</name> <modifier>*</modifier></type><name>vlc_http_res_get_redirect</name><parameter_list>(<parameter><decl><type><name><name>struct</name> <name>vlc_http_resource</name></name> <modifier>*</modifier></type></decl></parameter>)</parameter_list>;</function_decl>






<function_decl><type><name>char</name> <modifier>*</modifier></type><name>vlc_http_res_get_type</name><parameter_list>(<parameter><decl><type><name><name>struct</name> <name>vlc_http_resource</name></name> <modifier>*</modifier></type></decl></parameter>)</parameter_list>;</function_decl>




<function_decl><type><name><name>struct</name> <name>block_t</name></name> <modifier>*</modifier></type><name>vlc_http_res_read</name><parameter_list>(<parameter><decl><type><name><name>struct</name> <name>vlc_http_resource</name></name> <modifier>*</modifier></type></decl></parameter>)</parameter_list>;</function_decl>

<function_decl><type><name>int</name></type> <name>vlc_http_res_set_login</name><parameter_list>(<parameter><decl><type><name><name>struct</name> <name>vlc_http_resource</name></name> <modifier>*</modifier></type><name>res</name></decl></parameter>,
<parameter><decl><type><specifier>const</specifier> <name>char</name> <modifier>*</modifier></type><name>username</name></decl></parameter>, <parameter><decl><type><specifier>const</specifier> <name>char</name> <modifier>*</modifier></type><name>password</name></decl></parameter>)</parameter_list>;</function_decl>
<function_decl><type><name>char</name> <modifier>*</modifier></type><name>vlc_http_res_get_basic_realm</name><parameter_list>(<parameter><decl><type><name><name>struct</name> <name>vlc_http_resource</name></name> <modifier>*</modifier></type><name>res</name></decl></parameter>)</parameter_list>;</function_decl>


<cpp:endif>#<cpp:directive>endif</cpp:directive></cpp:endif>
</unit>
