<?xml version="1.0" encoding="UTF-8" standalone="yes"?>
<unit xmlns="http://www.srcML.org/srcML/src" xmlns:cpp="http://www.srcML.org/srcML/cpp" revision="1.0.0" language="C" filename="D:\Pesquisa\Projects\vlc-analysis\_cppstats_featurelocations\vlc\modules\codec\avcodec\fourcc.c">






















<cpp:if>#<cpp:directive>if</cpp:directive> <expr><call><name>defined</name><argument_list>(<argument><expr><name>HAVE_CONFIG_H</name></expr></argument>)</argument_list></call></expr></cpp:if>
<cpp:include>#<cpp:directive>include</cpp:directive> <cpp:file>&lt;config.h&gt;</cpp:file></cpp:include>
<cpp:endif>#<cpp:directive>endif</cpp:directive></cpp:endif>

<cpp:include>#<cpp:directive>include</cpp:directive> <cpp:file>&lt;vlc_common.h&gt;</cpp:file></cpp:include>
<cpp:include>#<cpp:directive>include</cpp:directive> <cpp:file>&lt;vlc_codec.h&gt;</cpp:file></cpp:include>

<cpp:include>#<cpp:directive>include</cpp:directive> <cpp:file>&lt;libavcodec/avcodec.h&gt;</cpp:file></cpp:include>
<cpp:include>#<cpp:directive>include</cpp:directive> <cpp:file>"avcodec.h"</cpp:file></cpp:include>





<struct>struct <name>vlc_avcodec_fourcc</name>
<block>{
<decl_stmt><decl><type><name>vlc_fourcc_t</name></type> <name>i_fourcc</name></decl>;</decl_stmt>
<decl_stmt><decl><type><name>unsigned</name></type> <name>i_codec</name></decl>;</decl_stmt>
}</block>;</struct>




<decl_stmt><decl><type><specifier>static</specifier> <specifier>const</specifier> <name><name>struct</name> <name>vlc_avcodec_fourcc</name></name></type> <name><name>video_codecs</name><index>[]</index></name> <init>=
<expr><block>{
<expr><block>{ <expr><name>VLC_CODEC_MP1V</name></expr>, <expr><name>AV_CODEC_ID_MPEG1VIDEO</name></expr> }</block></expr>,
<expr><block>{ <expr><name>VLC_CODEC_MP2V</name></expr>, <expr><name>AV_CODEC_ID_MPEG2VIDEO</name></expr> }</block></expr>, 
<expr><block>{ <expr><name>VLC_CODEC_MPGV</name></expr>, <expr><name>AV_CODEC_ID_MPEG2VIDEO</name></expr> }</block></expr>, 

<expr><block>{ <expr><name>VLC_CODEC_H261</name></expr>, <expr><name>AV_CODEC_ID_H261</name></expr> }</block></expr>,
<expr><block>{ <expr><name>VLC_CODEC_H263</name></expr>, <expr><name>AV_CODEC_ID_H263</name></expr> }</block></expr>,
<expr><block>{ <expr><name>VLC_CODEC_RV10</name></expr>, <expr><name>AV_CODEC_ID_RV10</name></expr> }</block></expr>,
<expr><block>{ <expr><name>VLC_CODEC_RV13</name></expr>, <expr><name>AV_CODEC_ID_RV10</name></expr> }</block></expr>,
<expr><block>{ <expr><name>VLC_CODEC_RV20</name></expr>, <expr><name>AV_CODEC_ID_RV20</name></expr> }</block></expr>,
<expr><block>{ <expr><name>VLC_CODEC_MJPG</name></expr>, <expr><name>AV_CODEC_ID_MJPEG</name></expr> }</block></expr>,
<expr><block>{ <expr><name>VLC_CODEC_MJPGB</name></expr>, <expr><name>AV_CODEC_ID_MJPEGB</name></expr> }</block></expr>,
<expr><block>{ <expr><name>VLC_CODEC_LJPG</name></expr>, <expr><name>AV_CODEC_ID_LJPEG</name></expr> }</block></expr>,
<expr><block>{ <expr><name>VLC_CODEC_SP5X</name></expr>, <expr><name>AV_CODEC_ID_SP5X</name></expr> }</block></expr>,
<expr><block>{ <expr><name>VLC_CODEC_JPEGLS</name></expr>, <expr><name>AV_CODEC_ID_JPEGLS</name></expr> }</block></expr>,
<expr><block>{ <expr><name>VLC_CODEC_MP4V</name></expr>, <expr><name>AV_CODEC_ID_MPEG4</name></expr> }</block></expr>,
<expr><block>{ <expr><name>VLC_CODEC_RGB32</name></expr>, <expr><name>AV_CODEC_ID_RAWVIDEO</name></expr> }</block></expr>,
<expr><block>{ <expr><name>VLC_CODEC_RGB24</name></expr>, <expr><name>AV_CODEC_ID_RAWVIDEO</name></expr> }</block></expr>,
<expr><block>{ <expr><name>VLC_CODEC_RGB16</name></expr>, <expr><name>AV_CODEC_ID_RAWVIDEO</name></expr> }</block></expr>,
<expr><block>{ <expr><name>VLC_CODEC_RGB8</name></expr>, <expr><name>AV_CODEC_ID_RAWVIDEO</name></expr> }</block></expr>,
<expr><block>{ <expr><name>VLC_CODEC_RGBA</name></expr>, <expr><name>AV_CODEC_ID_RAWVIDEO</name></expr> }</block></expr>,
<expr><block>{ <expr><name>VLC_CODEC_ARGB</name></expr>, <expr><name>AV_CODEC_ID_RAWVIDEO</name></expr> }</block></expr>,
<expr><block>{ <expr><name>VLC_CODEC_DIV1</name></expr>, <expr><name>AV_CODEC_ID_MSMPEG4V1</name></expr> }</block></expr>,
<expr><block>{ <expr><name>VLC_CODEC_DIV2</name></expr>, <expr><name>AV_CODEC_ID_MSMPEG4V2</name></expr> }</block></expr>,
<expr><block>{ <expr><name>VLC_CODEC_DIV3</name></expr>, <expr><name>AV_CODEC_ID_MSMPEG4V3</name></expr> }</block></expr>,
<expr><block>{ <expr><name>VLC_CODEC_WMV1</name></expr>, <expr><name>AV_CODEC_ID_WMV1</name></expr> }</block></expr>,
<expr><block>{ <expr><name>VLC_CODEC_WMV2</name></expr>, <expr><name>AV_CODEC_ID_WMV2</name></expr> }</block></expr>,
<expr><block>{ <expr><name>VLC_CODEC_H263P</name></expr>, <expr><name>AV_CODEC_ID_H263P</name></expr> }</block></expr>,
<expr><block>{ <expr><name>VLC_CODEC_H263I</name></expr>, <expr><name>AV_CODEC_ID_H263I</name></expr> }</block></expr>,
<expr><block>{ <expr><name>VLC_CODEC_FLV1</name></expr>, <expr><name>AV_CODEC_ID_FLV1</name></expr> }</block></expr>,
<expr><block>{ <expr><name>VLC_CODEC_SVQ1</name></expr>, <expr><name>AV_CODEC_ID_SVQ1</name></expr> }</block></expr>,
<expr><block>{ <expr><name>VLC_CODEC_SVQ3</name></expr>, <expr><name>AV_CODEC_ID_SVQ3</name></expr> }</block></expr>,
<expr><block>{ <expr><name>VLC_CODEC_DV</name></expr>, <expr><name>AV_CODEC_ID_DVVIDEO</name></expr> }</block></expr>,
<expr><block>{ <expr><name>VLC_CODEC_HUFFYUV</name></expr>, <expr><name>AV_CODEC_ID_HUFFYUV</name></expr> }</block></expr>,
<expr><block>{ <expr><name>VLC_CODEC_CYUV</name></expr>, <expr><name>AV_CODEC_ID_CYUV</name></expr> }</block></expr>,
<expr><block>{ <expr><name>VLC_CODEC_H264</name></expr>, <expr><name>AV_CODEC_ID_H264</name></expr> }</block></expr>,
<expr><block>{ <expr><name>VLC_CODEC_INDEO3</name></expr>, <expr><name>AV_CODEC_ID_INDEO3</name></expr> }</block></expr>,
<expr><block>{ <expr><name>VLC_CODEC_VP3</name></expr>, <expr><name>AV_CODEC_ID_VP3</name></expr> }</block></expr>,
<expr><block>{ <expr><name>VLC_CODEC_THEORA</name></expr>, <expr><name>AV_CODEC_ID_THEORA</name></expr> }</block></expr>,
<cpp:if>#<cpp:directive>if</cpp:directive> <expr><operator>(</operator> <operator>!</operator><call><name>defined</name><argument_list>( <argument><expr><name>WORDS_BIGENDIAN</name></expr></argument> )</argument_list></call> <operator>)</operator></expr></cpp:if>

<expr><block>{ <expr><name>VLC_CODEC_ASV1</name></expr>, <expr><name>AV_CODEC_ID_ASV1</name></expr> }</block></expr>,
<expr><block>{ <expr><name>VLC_CODEC_ASV2</name></expr>, <expr><name>AV_CODEC_ID_ASV2</name></expr> }</block></expr>,
<cpp:endif>#<cpp:directive>endif</cpp:directive></cpp:endif>
<expr><block>{ <expr><name>VLC_CODEC_FFV1</name></expr>, <expr><name>AV_CODEC_ID_FFV1</name></expr> }</block></expr>,
<expr><block>{ <expr><name>VLC_CODEC_4XM</name></expr>, <expr><name>AV_CODEC_ID_4XM</name></expr> }</block></expr>,
<expr><block>{ <expr><name>VLC_CODEC_VCR1</name></expr>, <expr><name>AV_CODEC_ID_VCR1</name></expr> }</block></expr>,
<expr><block>{ <expr><name>VLC_CODEC_CLJR</name></expr>, <expr><name>AV_CODEC_ID_CLJR</name></expr> }</block></expr>,
<expr><block>{ <expr><name>VLC_CODEC_MDEC</name></expr>, <expr><name>AV_CODEC_ID_MDEC</name></expr> }</block></expr>,
<expr><block>{ <expr><name>VLC_CODEC_ROQ</name></expr>, <expr><name>AV_CODEC_ID_ROQ</name></expr> }</block></expr>,
<expr><block>{ <expr><name>VLC_CODEC_INTERPLAY</name></expr>, <expr><name>AV_CODEC_ID_INTERPLAY_VIDEO</name></expr> }</block></expr>,
<expr><block>{ <expr><name>VLC_CODEC_XAN_WC3</name></expr>, <expr><name>AV_CODEC_ID_XAN_WC3</name></expr> }</block></expr>,
<expr><block>{ <expr><name>VLC_CODEC_XAN_WC4</name></expr>, <expr><name>AV_CODEC_ID_XAN_WC4</name></expr> }</block></expr>,
<expr><block>{ <expr><name>VLC_CODEC_RPZA</name></expr>, <expr><name>AV_CODEC_ID_RPZA</name></expr> }</block></expr>,
<expr><block>{ <expr><name>VLC_CODEC_CINEPAK</name></expr>, <expr><name>AV_CODEC_ID_CINEPAK</name></expr> }</block></expr>,
<expr><block>{ <expr><name>VLC_CODEC_WS_VQA</name></expr>, <expr><name>AV_CODEC_ID_WS_VQA</name></expr> }</block></expr>,
<expr><block>{ <expr><name>VLC_CODEC_MSRLE</name></expr>, <expr><name>AV_CODEC_ID_MSRLE</name></expr> }</block></expr>,
<expr><block>{ <expr><name>VLC_CODEC_MSVIDEO1</name></expr>, <expr><name>AV_CODEC_ID_MSVIDEO1</name></expr> }</block></expr>,
<expr><block>{ <expr><name>VLC_CODEC_IDCIN</name></expr>, <expr><name>AV_CODEC_ID_IDCIN</name></expr> }</block></expr>,
<expr><block>{ <expr><name>VLC_CODEC_8BPS</name></expr>, <expr><name>AV_CODEC_ID_8BPS</name></expr> }</block></expr>,
<expr><block>{ <expr><name>VLC_CODEC_SMC</name></expr>, <expr><name>AV_CODEC_ID_SMC</name></expr> }</block></expr>,
<expr><block>{ <expr><name>VLC_CODEC_FLIC</name></expr>, <expr><name>AV_CODEC_ID_FLIC</name></expr> }</block></expr>,
<expr><block>{ <expr><name>VLC_CODEC_TRUEMOTION1</name></expr>, <expr><name>AV_CODEC_ID_TRUEMOTION1</name></expr> }</block></expr>,
<expr><block>{ <expr><name>VLC_CODEC_VMDVIDEO</name></expr>, <expr><name>AV_CODEC_ID_VMDVIDEO</name></expr> }</block></expr>,
<expr><block>{ <expr><name>VLC_CODEC_LCL_MSZH</name></expr>, <expr><name>AV_CODEC_ID_MSZH</name></expr> }</block></expr>,
<expr><block>{ <expr><name>VLC_CODEC_LCL_ZLIB</name></expr>, <expr><name>AV_CODEC_ID_ZLIB</name></expr> }</block></expr>,
<expr><block>{ <expr><name>VLC_CODEC_QTRLE</name></expr>, <expr><name>AV_CODEC_ID_QTRLE</name></expr> }</block></expr>,
<expr><block>{ <expr><name>VLC_CODEC_TSCC</name></expr>, <expr><name>AV_CODEC_ID_TSCC</name></expr> }</block></expr>,
<expr><block>{ <expr><name>VLC_CODEC_ULTI</name></expr>, <expr><name>AV_CODEC_ID_ULTI</name></expr> }</block></expr>,
<expr><block>{ <expr><name>VLC_CODEC_QDRAW</name></expr>, <expr><name>AV_CODEC_ID_QDRAW</name></expr> }</block></expr>,
<expr><block>{ <expr><name>VLC_CODEC_VIXL</name></expr>, <expr><name>AV_CODEC_ID_VIXL</name></expr> }</block></expr>,
<expr><block>{ <expr><name>VLC_CODEC_QPEG</name></expr>, <expr><name>AV_CODEC_ID_QPEG</name></expr> }</block></expr>,
<expr><block>{ <expr><name>VLC_CODEC_PNG</name></expr>, <expr><name>AV_CODEC_ID_PNG</name></expr> }</block></expr>,
<expr><block>{ <expr><name>VLC_CODEC_PPM</name></expr>, <expr><name>AV_CODEC_ID_PPM</name></expr> }</block></expr>,

<expr><block>{ <expr><name>VLC_CODEC_PGM</name></expr>, <expr><name>AV_CODEC_ID_PGM</name></expr> }</block></expr>,
<expr><block>{ <expr><name>VLC_CODEC_PGMYUV</name></expr>, <expr><name>AV_CODEC_ID_PGMYUV</name></expr> }</block></expr>,
<expr><block>{ <expr><name>VLC_CODEC_PAM</name></expr>, <expr><name>AV_CODEC_ID_PAM</name></expr> }</block></expr>,
<expr><block>{ <expr><name>VLC_CODEC_FFVHUFF</name></expr>, <expr><name>AV_CODEC_ID_FFVHUFF</name></expr> }</block></expr>,
<expr><block>{ <expr><name>VLC_CODEC_RV30</name></expr>, <expr><name>AV_CODEC_ID_RV30</name></expr> }</block></expr>,
<expr><block>{ <expr><name>VLC_CODEC_RV40</name></expr>, <expr><name>AV_CODEC_ID_RV40</name></expr> }</block></expr>,
<expr><block>{ <expr><name>VLC_CODEC_VC1</name></expr>, <expr><name>AV_CODEC_ID_VC1</name></expr> }</block></expr>,
<expr><block>{ <expr><name>VLC_CODEC_WMVA</name></expr>, <expr><name>AV_CODEC_ID_VC1</name></expr> }</block></expr>,
<expr><block>{ <expr><name>VLC_CODEC_WMV3</name></expr>, <expr><name>AV_CODEC_ID_WMV3</name></expr> }</block></expr>,
<expr><block>{ <expr><name>VLC_CODEC_WMVP</name></expr>, <expr><name>AV_CODEC_ID_WMV3</name></expr> }</block></expr>,
<expr><block>{ <expr><name>VLC_CODEC_LOCO</name></expr>, <expr><name>AV_CODEC_ID_LOCO</name></expr> }</block></expr>,
<expr><block>{ <expr><name>VLC_CODEC_WNV1</name></expr>, <expr><name>AV_CODEC_ID_WNV1</name></expr> }</block></expr>,
<expr><block>{ <expr><name>VLC_CODEC_AASC</name></expr>, <expr><name>AV_CODEC_ID_AASC</name></expr> }</block></expr>,
<expr><block>{ <expr><name>VLC_CODEC_INDEO2</name></expr>, <expr><name>AV_CODEC_ID_INDEO2</name></expr> }</block></expr>,
<expr><block>{ <expr><name>VLC_CODEC_FRAPS</name></expr>, <expr><name>AV_CODEC_ID_FRAPS</name></expr> }</block></expr>,
<expr><block>{ <expr><name>VLC_CODEC_TRUEMOTION2</name></expr>, <expr><name>AV_CODEC_ID_TRUEMOTION2</name></expr> }</block></expr>,
<expr><block>{ <expr><name>VLC_CODEC_BMP</name></expr>, <expr><name>AV_CODEC_ID_BMP</name></expr> }</block></expr>,
<expr><block>{ <expr><name>VLC_CODEC_CSCD</name></expr>, <expr><name>AV_CODEC_ID_CSCD</name></expr> }</block></expr>,
<expr><block>{ <expr><name>VLC_CODEC_MMVIDEO</name></expr>, <expr><name>AV_CODEC_ID_MMVIDEO</name></expr> }</block></expr>,
<expr><block>{ <expr><name>VLC_CODEC_ZMBV</name></expr>, <expr><name>AV_CODEC_ID_ZMBV</name></expr> }</block></expr>,
<expr><block>{ <expr><name>VLC_CODEC_AVS</name></expr>, <expr><name>AV_CODEC_ID_AVS</name></expr> }</block></expr>,
<expr><block>{ <expr><name>VLC_CODEC_SMACKVIDEO</name></expr>, <expr><name>AV_CODEC_ID_SMACKVIDEO</name></expr> }</block></expr>,
<expr><block>{ <expr><name>VLC_CODEC_NUV</name></expr>, <expr><name>AV_CODEC_ID_NUV</name></expr> }</block></expr>,
<expr><block>{ <expr><name>VLC_CODEC_KMVC</name></expr>, <expr><name>AV_CODEC_ID_KMVC</name></expr> }</block></expr>,
<expr><block>{ <expr><name>VLC_CODEC_FLASHSV</name></expr>, <expr><name>AV_CODEC_ID_FLASHSV</name></expr> }</block></expr>,
<expr><block>{ <expr><name>VLC_CODEC_CAVS</name></expr>, <expr><name>AV_CODEC_ID_CAVS</name></expr> }</block></expr>,
<expr><block>{ <expr><name>VLC_CODEC_JPEG2000</name></expr>, <expr><name>AV_CODEC_ID_JPEG2000</name></expr> }</block></expr>,
<expr><block>{ <expr><name>VLC_CODEC_VMNC</name></expr>, <expr><name>AV_CODEC_ID_VMNC</name></expr> }</block></expr>,
<expr><block>{ <expr><name>VLC_CODEC_VP5</name></expr>, <expr><name>AV_CODEC_ID_VP5</name></expr> }</block></expr>,
<expr><block>{ <expr><name>VLC_CODEC_VP6</name></expr>, <expr><name>AV_CODEC_ID_VP6</name></expr> }</block></expr>,
<expr><block>{ <expr><name>VLC_CODEC_VP6F</name></expr>, <expr><name>AV_CODEC_ID_VP6F</name></expr> }</block></expr>,
<expr><block>{ <expr><name>VLC_CODEC_TARGA</name></expr>, <expr><name>AV_CODEC_ID_TARGA</name></expr> }</block></expr>,
<expr><block>{ <expr><name>VLC_CODEC_DSICINVIDEO</name></expr>, <expr><name>AV_CODEC_ID_DSICINVIDEO</name></expr> }</block></expr>,
<expr><block>{ <expr><name>VLC_CODEC_TIERTEXSEQVIDEO</name></expr>, <expr><name>AV_CODEC_ID_TIERTEXSEQVIDEO</name></expr> }</block></expr>,
<expr><block>{ <expr><name>VLC_CODEC_TIFF</name></expr>, <expr><name>AV_CODEC_ID_TIFF</name></expr> }</block></expr>,
<expr><block>{ <expr><name>VLC_CODEC_GIF</name></expr>, <expr><name>AV_CODEC_ID_GIF</name></expr> }</block></expr>,
<expr><block>{ <expr><name>VLC_CODEC_DXA</name></expr>, <expr><name>AV_CODEC_ID_DXA</name></expr> }</block></expr>,
<expr><block>{ <expr><name>VLC_CODEC_DNXHD</name></expr>, <expr><name>AV_CODEC_ID_DNXHD</name></expr> }</block></expr>,
<expr><block>{ <expr><name>VLC_CODEC_THP</name></expr>, <expr><name>AV_CODEC_ID_THP</name></expr> }</block></expr>,
<expr><block>{ <expr><name>VLC_CODEC_SGI</name></expr>, <expr><name>AV_CODEC_ID_SGI</name></expr> }</block></expr>,
<expr><block>{ <expr><name>VLC_CODEC_C93</name></expr>, <expr><name>AV_CODEC_ID_C93</name></expr> }</block></expr>,
<expr><block>{ <expr><name>VLC_CODEC_BETHSOFTVID</name></expr>, <expr><name>AV_CODEC_ID_BETHSOFTVID</name></expr> }</block></expr>,

<expr><block>{ <expr><name>VLC_CODEC_TXD</name></expr>, <expr><name>AV_CODEC_ID_TXD</name></expr> }</block></expr>,
<expr><block>{ <expr><name>VLC_CODEC_VP6A</name></expr>, <expr><name>AV_CODEC_ID_VP6A</name></expr> }</block></expr>,
<expr><block>{ <expr><name>VLC_CODEC_AMV</name></expr>, <expr><name>AV_CODEC_ID_AMV</name></expr> }</block></expr>,
<expr><block>{ <expr><name>VLC_CODEC_VB</name></expr>, <expr><name>AV_CODEC_ID_VB</name></expr> }</block></expr>,
<expr><block>{ <expr><name>VLC_CODEC_PCX</name></expr>, <expr><name>AV_CODEC_ID_PCX</name></expr> }</block></expr>,

<expr><block>{ <expr><name>VLC_CODEC_INDEO4</name></expr>, <expr><name>AV_CODEC_ID_INDEO4</name></expr> }</block></expr>,
<expr><block>{ <expr><name>VLC_CODEC_INDEO5</name></expr>, <expr><name>AV_CODEC_ID_INDEO5</name></expr> }</block></expr>,
<expr><block>{ <expr><name>VLC_CODEC_MIMIC</name></expr>, <expr><name>AV_CODEC_ID_MIMIC</name></expr> }</block></expr>,
<expr><block>{ <expr><name>VLC_CODEC_RL2</name></expr>, <expr><name>AV_CODEC_ID_RL2</name></expr> }</block></expr>,
<expr><block>{ <expr><name>VLC_CODEC_ESCAPE124</name></expr>, <expr><name>AV_CODEC_ID_ESCAPE124</name></expr> }</block></expr>,
<expr><block>{ <expr><name>VLC_CODEC_DIRAC</name></expr>, <expr><name>AV_CODEC_ID_DIRAC</name></expr> }</block></expr>,
<expr><block>{ <expr><name>VLC_CODEC_BFI</name></expr>, <expr><name>AV_CODEC_ID_BFI</name></expr> }</block></expr>,
<expr><block>{ <expr><name>VLC_CODEC_CMV</name></expr>, <expr><name>AV_CODEC_ID_CMV</name></expr> }</block></expr>,
<expr><block>{ <expr><name>VLC_CODEC_MOTIONPIXELS</name></expr>, <expr><name>AV_CODEC_ID_MOTIONPIXELS</name></expr> }</block></expr>,
<expr><block>{ <expr><name>VLC_CODEC_TGV</name></expr>, <expr><name>AV_CODEC_ID_TGV</name></expr> }</block></expr>,
<expr><block>{ <expr><name>VLC_CODEC_TGQ</name></expr>, <expr><name>AV_CODEC_ID_TGQ</name></expr> }</block></expr>,
<expr><block>{ <expr><name>VLC_CODEC_TQI</name></expr>, <expr><name>AV_CODEC_ID_TQI</name></expr> }</block></expr>,
<expr><block>{ <expr><name>VLC_CODEC_AURA</name></expr>, <expr><name>AV_CODEC_ID_AURA</name></expr> }</block></expr>,


<expr><block>{ <expr><name>VLC_CODEC_TMV</name></expr>, <expr><name>AV_CODEC_ID_TMV</name></expr> }</block></expr>,
<expr><block>{ <expr><name>VLC_CODEC_V210</name></expr>, <expr><name>AV_CODEC_ID_V210</name></expr> }</block></expr>,
<cpp:if>#<cpp:directive>if</cpp:directive> <expr><name>LIBAVCODEC_VERSION_INT</name> <operator>&gt;=</operator> <call><name>AV_VERSION_INT</name><argument_list>( <argument><expr><literal type="number">54</literal><operator>,</operator> <literal type="number">50</literal><operator>,</operator> <literal type="number">100</literal></expr></argument> )</argument_list></call> <operator>&amp;&amp;</operator> <name>LIBAVCODEC_VERSION_MICRO</name> <operator>&gt;=</operator> <literal type="number">100</literal></expr></cpp:if>
<expr><block>{ <expr><name>VLC_CODEC_VUYA</name></expr>, <expr><name>AV_CODEC_ID_AYUV</name></expr> }</block></expr>,
<cpp:endif>#<cpp:directive>endif</cpp:directive></cpp:endif>

<expr><block>{ <expr><name>VLC_CODEC_MAD</name></expr>, <expr><name>AV_CODEC_ID_MAD</name></expr> }</block></expr>,
<expr><block>{ <expr><name>VLC_CODEC_FRWU</name></expr>, <expr><name>AV_CODEC_ID_FRWU</name></expr> }</block></expr>,
<expr><block>{ <expr><name>VLC_CODEC_FLASHSV2</name></expr>, <expr><name>AV_CODEC_ID_FLASHSV2</name></expr> }</block></expr>,


<expr><block>{ <expr><name>VLC_CODEC_ANM</name></expr>, <expr><name>AV_CODEC_ID_ANM</name></expr> }</block></expr>,
<expr><block>{ <expr><name>VLC_CODEC_BINKVIDEO</name></expr>, <expr><name>AV_CODEC_ID_BINKVIDEO</name></expr> }</block></expr>,


<expr><block>{ <expr><name>VLC_CODEC_KGV1</name></expr>, <expr><name>AV_CODEC_ID_KGV1</name></expr> }</block></expr>,
<expr><block>{ <expr><name>VLC_CODEC_YOP</name></expr>, <expr><name>AV_CODEC_ID_YOP</name></expr> }</block></expr>,
<cpp:if>#<cpp:directive>if</cpp:directive> <expr><name>LIBAVCODEC_VERSION_INT</name> <operator>&gt;=</operator> <call><name>AV_VERSION_INT</name><argument_list>( <argument><expr><literal type="number">58</literal><operator>,</operator> <literal type="number">53</literal><operator>,</operator> <literal type="number">100</literal></expr></argument> )</argument_list></call> <operator>&amp;&amp;</operator> <name>LIBAVCODEC_VERSION_MICRO</name> <operator>&gt;=</operator> <literal type="number">100</literal></expr></cpp:if>
<expr><block>{ <expr><name>VLC_CODEC_VP4</name></expr>, <expr><name>AV_CODEC_ID_VP4</name></expr> }</block></expr>,
<cpp:endif>#<cpp:directive>endif</cpp:directive></cpp:endif>
<expr><block>{ <expr><name>VLC_CODEC_VP8</name></expr>, <expr><name>AV_CODEC_ID_VP8</name></expr> }</block></expr>,





<expr><block>{ <expr><name>VLC_CODEC_MXPEG</name></expr>, <expr><name>AV_CODEC_ID_MXPEG</name></expr> }</block></expr>,
<expr><block>{ <expr><name>VLC_CODEC_LAGARITH</name></expr>, <expr><name>AV_CODEC_ID_LAGARITH</name></expr> }</block></expr>,
<expr><block>{ <expr><name>VLC_CODEC_PRORES</name></expr>, <expr><name>AV_CODEC_ID_PRORES</name></expr> }</block></expr>,
<expr><block>{ <expr><name>VLC_CODEC_JV</name></expr>, <expr><name>AV_CODEC_ID_JV</name></expr> }</block></expr>,
<expr><block>{ <expr><name>VLC_CODEC_DFA</name></expr>, <expr><name>AV_CODEC_ID_DFA</name></expr> }</block></expr>,
<expr><block>{ <expr><name>VLC_CODEC_WMVP</name></expr>, <expr><name>AV_CODEC_ID_WMV3IMAGE</name></expr> }</block></expr>,
<expr><block>{ <expr><name>VLC_CODEC_WMVP2</name></expr>, <expr><name>AV_CODEC_ID_VC1IMAGE</name></expr> }</block></expr>,
<expr><block>{ <expr><name>VLC_CODEC_UTVIDEO</name></expr>, <expr><name>AV_CODEC_ID_UTVIDEO</name></expr> }</block></expr>,
<expr><block>{ <expr><name>VLC_CODEC_BMVVIDEO</name></expr>, <expr><name>AV_CODEC_ID_BMV_VIDEO</name></expr> }</block></expr>,
<expr><block>{ <expr><name>VLC_CODEC_VBLE</name></expr>, <expr><name>AV_CODEC_ID_VBLE</name></expr> }</block></expr>,
<expr><block>{ <expr><name>VLC_CODEC_DXTORY</name></expr>, <expr><name>AV_CODEC_ID_DXTORY</name></expr> }</block></expr>,
<expr><block>{ <expr><name>VLC_CODEC_V410</name></expr>, <expr><name>AV_CODEC_ID_V410</name></expr> }</block></expr>,

<expr><block>{ <expr><name>VLC_CODEC_CDXL</name></expr>, <expr><name>AV_CODEC_ID_CDXL</name></expr> }</block></expr>,


<expr><block>{ <expr><name>VLC_CODEC_MSS1</name></expr>, <expr><name>AV_CODEC_ID_MSS1</name></expr> }</block></expr>,
<expr><block>{ <expr><name>VLC_CODEC_MSA1</name></expr>, <expr><name>AV_CODEC_ID_MSA1</name></expr> }</block></expr>,
<expr><block>{ <expr><name>VLC_CODEC_TSC2</name></expr>, <expr><name>AV_CODEC_ID_TSCC2</name></expr> }</block></expr>,
<expr><block>{ <expr><name>VLC_CODEC_MTS2</name></expr>, <expr><name>AV_CODEC_ID_MTS2</name></expr> }</block></expr>,
<expr><block>{ <expr><name>VLC_CODEC_CLLC</name></expr>, <expr><name>AV_CODEC_ID_CLLC</name></expr> }</block></expr>,
<expr><block>{ <expr><name>VLC_CODEC_MSS2</name></expr>, <expr><name>AV_CODEC_ID_MSS2</name></expr> }</block></expr>,
<expr><block>{ <expr><name>VLC_CODEC_VP9</name></expr>, <expr><name>AV_CODEC_ID_VP9</name></expr> }</block></expr>,
<cpp:if>#<cpp:directive>if</cpp:directive> <expr><call><name>LIBAVCODEC_VERSION_CHECK</name><argument_list>( <argument><expr><literal type="number">57</literal><operator>,</operator> <literal type="number">26</literal><operator>,</operator> <literal type="number">0</literal><operator>,</operator> <literal type="number">83</literal><operator>,</operator> <literal type="number">101</literal></expr></argument> )</argument_list></call></expr></cpp:if>
<expr><block>{ <expr><name>VLC_CODEC_AV1</name></expr>, <expr><name>AV_CODEC_ID_AV1</name></expr> }</block></expr>,
<cpp:endif>#<cpp:directive>endif</cpp:directive></cpp:endif>
<expr><block>{ <expr><name>VLC_CODEC_ICOD</name></expr>, <expr><name>AV_CODEC_ID_AIC</name></expr> }</block></expr>,

<expr><block>{ <expr><name>VLC_CODEC_G2M4</name></expr>, <expr><name>AV_CODEC_ID_G2M</name></expr> }</block></expr>,
<expr><block>{ <expr><name>VLC_CODEC_G2M2</name></expr>, <expr><name>AV_CODEC_ID_G2M</name></expr> }</block></expr>,
<expr><block>{ <expr><name>VLC_CODEC_G2M3</name></expr>, <expr><name>AV_CODEC_ID_G2M</name></expr> }</block></expr>,

<expr><block>{ <expr><name>VLC_CODEC_HNM4_VIDEO</name></expr>, <expr><name>AV_CODEC_ID_HNM4_VIDEO</name></expr> }</block></expr>,
<expr><block>{ <expr><name>VLC_CODEC_HEVC</name></expr>, <expr><name>AV_CODEC_ID_HEVC</name></expr> }</block></expr>,

<expr><block>{ <expr><name>VLC_CODEC_FIC</name></expr> , <expr><name>AV_CODEC_ID_FIC</name></expr> }</block></expr>,





<expr><block>{ <expr><name>VLC_CODEC_VP7</name></expr> , <expr><name>AV_CODEC_ID_VP7</name></expr> }</block></expr>,




<expr><block>{ <expr><name>VLC_CODEC_HQX</name></expr>, <expr><name>AV_CODEC_ID_HQX</name></expr> }</block></expr>,

<expr><block>{ <expr><name>VLC_CODEC_TDSC</name></expr>, <expr><name>AV_CODEC_ID_TDSC</name></expr> }</block></expr>,

<expr><block>{ <expr><name>VLC_CODEC_HQ_HQA</name></expr>, <expr><name>AV_CODEC_ID_HQ_HQA</name></expr> }</block></expr>,

<expr><block>{ <expr><name>VLC_CODEC_HAP</name></expr>, <expr><name>AV_CODEC_ID_HAP</name></expr> }</block></expr>,


<expr><block>{ <expr><name>VLC_CODEC_DXV</name></expr>, <expr><name>AV_CODEC_ID_DXV</name></expr> }</block></expr>,








<cpp:if>#<cpp:directive>if</cpp:directive> <expr><name>LIBAVCODEC_VERSION_MICRO</name> <operator>&gt;=</operator> <literal type="number">100</literal></expr></cpp:if>
<expr><block>{ <expr><name>VLC_CODEC_V308</name></expr>, <expr><name>AV_CODEC_ID_V308</name></expr> }</block></expr>,
<expr><block>{ <expr><name>VLC_CODEC_V408</name></expr>, <expr><name>AV_CODEC_ID_V408</name></expr> }</block></expr>,
<expr><block>{ <expr><name>VLC_CODEC_YUV4</name></expr>, <expr><name>AV_CODEC_ID_YUV4</name></expr> }</block></expr>,
<cpp:endif>#<cpp:directive>endif</cpp:directive></cpp:endif>











<cpp:if>#<cpp:directive>if</cpp:directive> <expr><call><name>LIBAVCODEC_VERSION_CHECK</name><argument_list>( <argument><expr><literal type="number">58</literal><operator>,</operator> <literal type="number">0</literal><operator>,</operator> <literal type="number">0</literal><operator>,</operator> <literal type="number">1</literal><operator>,</operator> <literal type="number">100</literal></expr></argument> )</argument_list></call></expr></cpp:if>
<expr><block>{ <expr><name>VLC_CODEC_MAGICYUV</name></expr>, <expr><name>AV_CODEC_ID_MAGICYUV</name></expr> }</block></expr>,
<cpp:endif>#<cpp:directive>endif</cpp:directive></cpp:endif>

<cpp:if>#<cpp:directive>if</cpp:directive> <expr><name>LIBAVCODEC_VERSION_MICRO</name> <operator>&gt;=</operator> <literal type="number">100</literal></expr></cpp:if> 
<cpp:if>#<cpp:directive>if</cpp:directive> <expr><name>LIBAVCODEC_VERSION_INT</name> <operator>&gt;=</operator> <call><name>AV_VERSION_INT</name><argument_list>( <argument><expr><literal type="number">57</literal><operator>,</operator> <literal type="number">24</literal><operator>,</operator> <literal type="number">102</literal></expr></argument> )</argument_list></call></expr></cpp:if>
<expr><block>{ <expr><name>VLC_CODEC_CINEFORM</name></expr>, <expr><name>AV_CODEC_ID_CFHD</name></expr> }</block></expr>,
<cpp:endif>#<cpp:directive>endif</cpp:directive></cpp:endif>

<cpp:if>#<cpp:directive>if</cpp:directive> <expr><name>LIBAVCODEC_VERSION_INT</name> <operator>&gt;=</operator> <call><name>AV_VERSION_INT</name><argument_list>( <argument><expr><literal type="number">57</literal><operator>,</operator> <literal type="number">70</literal><operator>,</operator> <literal type="number">100</literal></expr></argument> )</argument_list></call></expr></cpp:if>
<expr><block>{ <expr><name>VLC_CODEC_PIXLET</name></expr>, <expr><name>AV_CODEC_ID_PIXLET</name></expr> }</block></expr>,
<cpp:endif>#<cpp:directive>endif</cpp:directive></cpp:endif>

<cpp:if>#<cpp:directive>if</cpp:directive> <expr><name>LIBAVCODEC_VERSION_INT</name> <operator>&gt;=</operator> <call><name>AV_VERSION_INT</name><argument_list>( <argument><expr><literal type="number">57</literal><operator>,</operator> <literal type="number">71</literal><operator>,</operator> <literal type="number">101</literal></expr></argument> )</argument_list></call></expr></cpp:if>
<expr><block>{ <expr><name>VLC_CODEC_SPEEDHQ</name></expr>, <expr><name>AV_CODEC_ID_SPEEDHQ</name></expr> }</block></expr>,
<cpp:endif>#<cpp:directive>endif</cpp:directive></cpp:endif>

<cpp:if>#<cpp:directive>if</cpp:directive> <expr><name>LIBAVCODEC_VERSION_INT</name> <operator>&gt;=</operator> <call><name>AV_VERSION_INT</name><argument_list>( <argument><expr><literal type="number">57</literal><operator>,</operator> <literal type="number">79</literal><operator>,</operator> <literal type="number">100</literal></expr></argument> )</argument_list></call></expr></cpp:if>
<expr><block>{ <expr><name>VLC_CODEC_FMVC</name></expr>, <expr><name>AV_CODEC_ID_FMVC</name></expr> }</block></expr>,
<cpp:endif>#<cpp:directive>endif</cpp:directive></cpp:endif>

<cpp:if>#<cpp:directive>if</cpp:directive> <expr><name>LIBAVCODEC_VERSION_INT</name> <operator>&gt;=</operator> <call><name>AV_VERSION_INT</name><argument_list>( <argument><expr><literal type="number">58</literal><operator>,</operator> <literal type="number">24</literal><operator>,</operator> <literal type="number">100</literal></expr></argument> )</argument_list></call></expr></cpp:if>
<expr><block>{ <expr><name>VLC_CODEC_IMM4</name></expr>, <expr><name>AV_CODEC_ID_IMM4</name></expr> }</block></expr>,
<cpp:endif>#<cpp:directive>endif</cpp:directive></cpp:endif>

<cpp:if>#<cpp:directive>if</cpp:directive> <expr><name>LIBAVCODEC_VERSION_INT</name> <operator>&gt;=</operator> <call><name>AV_VERSION_INT</name><argument_list>( <argument><expr><literal type="number">58</literal><operator>,</operator> <literal type="number">49</literal><operator>,</operator> <literal type="number">100</literal></expr></argument> )</argument_list></call></expr></cpp:if>
<expr><block>{ <expr><name>VLC_CODEC_AGM</name></expr>, <expr><name>AV_CODEC_ID_AGM</name></expr> }</block></expr>,
<cpp:endif>#<cpp:directive>endif</cpp:directive></cpp:endif>

<cpp:if>#<cpp:directive>if</cpp:directive> <expr><name>LIBAVCODEC_VERSION_INT</name> <operator>&gt;=</operator> <call><name>AV_VERSION_INT</name><argument_list>( <argument><expr><literal type="number">58</literal><operator>,</operator> <literal type="number">56</literal><operator>,</operator> <literal type="number">100</literal></expr></argument> )</argument_list></call></expr></cpp:if>
<expr><block>{ <expr><name>VLC_CODEC_IMM5</name></expr>, <expr><name>AV_CODEC_ID_IMM5</name></expr> }</block></expr>,
<cpp:endif>#<cpp:directive>endif</cpp:directive></cpp:endif>
<cpp:endif>#<cpp:directive>endif</cpp:directive></cpp:endif> 
}</block></expr></init></decl>;</decl_stmt>




<decl_stmt><decl><type><specifier>static</specifier> <specifier>const</specifier> <name><name>struct</name> <name>vlc_avcodec_fourcc</name></name></type> <name><name>audio_codecs</name><index>[]</index></name> <init>=
<expr><block>{

<expr><block>{ <expr><name>VLC_CODEC_S16L</name></expr>, <expr><name>AV_CODEC_ID_PCM_S16LE</name></expr> }</block></expr>,
<expr><block>{ <expr><name>VLC_CODEC_S16B</name></expr>, <expr><name>AV_CODEC_ID_PCM_S16BE</name></expr> }</block></expr>,
<expr><block>{ <expr><name>VLC_CODEC_U16L</name></expr>, <expr><name>AV_CODEC_ID_PCM_U16LE</name></expr> }</block></expr>,
<expr><block>{ <expr><name>VLC_CODEC_U16B</name></expr>, <expr><name>AV_CODEC_ID_PCM_U16BE</name></expr> }</block></expr>,
<expr><block>{ <expr><name>VLC_CODEC_S8</name></expr>, <expr><name>AV_CODEC_ID_PCM_S8</name></expr> }</block></expr>,
<expr><block>{ <expr><name>VLC_CODEC_U8</name></expr>, <expr><name>AV_CODEC_ID_PCM_U8</name></expr> }</block></expr>,
<expr><block>{ <expr><name>VLC_CODEC_MULAW</name></expr>, <expr><name>AV_CODEC_ID_PCM_MULAW</name></expr> }</block></expr>,
<expr><block>{ <expr><name>VLC_CODEC_ALAW</name></expr>, <expr><name>AV_CODEC_ID_PCM_ALAW</name></expr> }</block></expr>,
<expr><block>{ <expr><name>VLC_CODEC_S32L</name></expr>, <expr><name>AV_CODEC_ID_PCM_S32LE</name></expr> }</block></expr>,
<expr><block>{ <expr><name>VLC_CODEC_S32B</name></expr>, <expr><name>AV_CODEC_ID_PCM_S32BE</name></expr> }</block></expr>,
<expr><block>{ <expr><name>VLC_CODEC_U32L</name></expr>, <expr><name>AV_CODEC_ID_PCM_U32LE</name></expr> }</block></expr>,
<expr><block>{ <expr><name>VLC_CODEC_U32B</name></expr>, <expr><name>AV_CODEC_ID_PCM_U32BE</name></expr> }</block></expr>,
<expr><block>{ <expr><name>VLC_CODEC_S24L</name></expr>, <expr><name>AV_CODEC_ID_PCM_S24LE</name></expr> }</block></expr>,
<expr><block>{ <expr><name>VLC_CODEC_S24B</name></expr>, <expr><name>AV_CODEC_ID_PCM_S24BE</name></expr> }</block></expr>,
<expr><block>{ <expr><name>VLC_CODEC_U24L</name></expr>, <expr><name>AV_CODEC_ID_PCM_U24LE</name></expr> }</block></expr>,
<expr><block>{ <expr><name>VLC_CODEC_U24B</name></expr>, <expr><name>AV_CODEC_ID_PCM_U24BE</name></expr> }</block></expr>,
<expr><block>{ <expr><name>VLC_CODEC_S24DAUD</name></expr>, <expr><name>AV_CODEC_ID_PCM_S24DAUD</name></expr> }</block></expr>,

<expr><block>{ <expr><name>VLC_CODEC_S16L_PLANAR</name></expr>, <expr><name>AV_CODEC_ID_PCM_S16LE_PLANAR</name></expr> }</block></expr>,

<expr><block>{ <expr><name>VLC_CODEC_F32B</name></expr>, <expr><name>AV_CODEC_ID_PCM_F32BE</name></expr> }</block></expr>,
<expr><block>{ <expr><name>VLC_CODEC_F32L</name></expr>, <expr><name>AV_CODEC_ID_PCM_F32LE</name></expr> }</block></expr>,
<expr><block>{ <expr><name>VLC_CODEC_F64B</name></expr>, <expr><name>AV_CODEC_ID_PCM_F64BE</name></expr> }</block></expr>,
<expr><block>{ <expr><name>VLC_CODEC_F64L</name></expr>, <expr><name>AV_CODEC_ID_PCM_F64LE</name></expr> }</block></expr>,
<expr><block>{ <expr><name>VLC_CODEC_BD_LPCM</name></expr>, <expr><name>AV_CODEC_ID_PCM_BLURAY</name></expr> }</block></expr>,








<expr><block>{ <expr><name>VLC_CODEC_ADPCM_IMA_QT</name></expr>, <expr><name>AV_CODEC_ID_ADPCM_IMA_QT</name></expr> }</block></expr>,
<expr><block>{ <expr><name>VLC_CODEC_ADPCM_IMA_WAV</name></expr>, <expr><name>AV_CODEC_ID_ADPCM_IMA_WAV</name></expr> }</block></expr>,


<expr><block>{ <expr><name>VLC_CODEC_ADPCM_IMA_WS</name></expr>, <expr><name>AV_CODEC_ID_ADPCM_IMA_WS</name></expr> }</block></expr>,

<expr><block>{ <expr><name>VLC_CODEC_ADPCM_MS</name></expr>, <expr><name>AV_CODEC_ID_ADPCM_MS</name></expr> }</block></expr>,
<expr><block>{ <expr><name>VLC_CODEC_ADPCM_4XM</name></expr>, <expr><name>AV_CODEC_ID_ADPCM_4XM</name></expr> }</block></expr>,
<expr><block>{ <expr><name>VLC_CODEC_ADPCM_XA</name></expr>, <expr><name>AV_CODEC_ID_ADPCM_XA</name></expr> }</block></expr>,
<expr><block>{ <expr><name>VLC_CODEC_ADPCM_ADX</name></expr>, <expr><name>AV_CODEC_ID_ADPCM_ADX</name></expr> }</block></expr>,
<expr><block>{ <expr><name>VLC_CODEC_ADPCM_EA</name></expr>, <expr><name>AV_CODEC_ID_ADPCM_EA</name></expr> }</block></expr>,
<expr><block>{ <expr><name>VLC_CODEC_ADPCM_G726</name></expr>, <expr><name>AV_CODEC_ID_ADPCM_G726</name></expr> }</block></expr>,
<expr><block>{ <expr><name>VLC_CODEC_ADPCM_CREATIVE</name></expr>, <expr><name>AV_CODEC_ID_ADPCM_CT</name></expr> }</block></expr>,
<expr><block>{ <expr><name>VLC_CODEC_ADPCM_SWF</name></expr>, <expr><name>AV_CODEC_ID_ADPCM_SWF</name></expr> }</block></expr>,
<expr><block>{ <expr><name>VLC_CODEC_ADPCM_YAMAHA</name></expr>, <expr><name>AV_CODEC_ID_ADPCM_YAMAHA</name></expr> }</block></expr>,
<expr><block>{ <expr><name>VLC_CODEC_ADPCM_SBPRO_4</name></expr>, <expr><name>AV_CODEC_ID_ADPCM_SBPRO_4</name></expr> }</block></expr>,
<expr><block>{ <expr><name>VLC_CODEC_ADPCM_SBPRO_3</name></expr>, <expr><name>AV_CODEC_ID_ADPCM_SBPRO_3</name></expr> }</block></expr>,
<expr><block>{ <expr><name>VLC_CODEC_ADPCM_SBPRO_2</name></expr>, <expr><name>AV_CODEC_ID_ADPCM_SBPRO_2</name></expr> }</block></expr>,
<expr><block>{ <expr><name>VLC_CODEC_ADPCM_THP</name></expr>, <expr><name>AV_CODEC_ID_ADPCM_THP</name></expr> }</block></expr>,
<expr><block>{ <expr><name>VLC_CODEC_ADPCM_IMA_AMV</name></expr>, <expr><name>AV_CODEC_ID_ADPCM_IMA_AMV</name></expr> }</block></expr>,
<expr><block>{ <expr><name>VLC_CODEC_ADPCM_EA_R1</name></expr>, <expr><name>AV_CODEC_ID_ADPCM_EA_R1</name></expr> }</block></expr>,


<expr><block>{ <expr><name>VLC_CODEC_ADPCM_IMA_EA_SEAD</name></expr>, <expr><name>AV_CODEC_ID_ADPCM_IMA_EA_SEAD</name></expr> }</block></expr>,




<expr><block>{ <expr><name>VLC_CODEC_ADPCM_G722</name></expr>, <expr><name>AV_CODEC_ID_ADPCM_G722</name></expr> }</block></expr>,
<expr><block>{ <expr><name>VLC_CODEC_ADPCM_IMA_APC</name></expr>, <expr><name>AV_CODEC_ID_ADPCM_IMA_APC</name></expr> }</block></expr>,








<expr><block>{ <expr><name>VLC_CODEC_AMR_NB</name></expr>, <expr><name>AV_CODEC_ID_AMR_NB</name></expr> }</block></expr>,
<expr><block>{ <expr><name>VLC_CODEC_AMR_WB</name></expr>, <expr><name>AV_CODEC_ID_AMR_WB</name></expr> }</block></expr>,


<expr><block>{ <expr><name>VLC_CODEC_RA_144</name></expr>, <expr><name>AV_CODEC_ID_RA_144</name></expr> }</block></expr>,
<expr><block>{ <expr><name>VLC_CODEC_RA_288</name></expr>, <expr><name>AV_CODEC_ID_RA_288</name></expr> }</block></expr>,


<expr><block>{ <expr><name>VLC_CODEC_ROQ_DPCM</name></expr>, <expr><name>AV_CODEC_ID_ROQ_DPCM</name></expr> }</block></expr>,
<expr><block>{ <expr><name>VLC_CODEC_INTERPLAY_DPCM</name></expr>, <expr><name>AV_CODEC_ID_INTERPLAY_DPCM</name></expr> }</block></expr>,




<expr><block>{ <expr><name>VLC_CODEC_MPGA</name></expr>, <expr><name>AV_CODEC_ID_MP2</name></expr> }</block></expr>,
<expr><block>{ <expr><name>VLC_CODEC_MP2</name></expr>, <expr><name>AV_CODEC_ID_MP2</name></expr> }</block></expr>,
<expr><block>{ <expr><name>VLC_CODEC_MP3</name></expr>, <expr><name>AV_CODEC_ID_MP3</name></expr> }</block></expr>,
<expr><block>{ <expr><name>VLC_CODEC_MP4A</name></expr>, <expr><name>AV_CODEC_ID_AAC</name></expr> }</block></expr>,
<expr><block>{ <expr><name>VLC_CODEC_A52</name></expr>, <expr><name>AV_CODEC_ID_AC3</name></expr> }</block></expr>,
<expr><block>{ <expr><name>VLC_CODEC_DTS</name></expr>, <expr><name>AV_CODEC_ID_DTS</name></expr> }</block></expr>,
<expr><block>{ <expr><name>VLC_CODEC_VORBIS</name></expr>, <expr><name>AV_CODEC_ID_VORBIS</name></expr> }</block></expr>,
<expr><block>{ <expr><name>VLC_CODEC_DVAUDIO</name></expr>, <expr><name>AV_CODEC_ID_DVAUDIO</name></expr> }</block></expr>,
<expr><block>{ <expr><name>VLC_CODEC_WMA1</name></expr>, <expr><name>AV_CODEC_ID_WMAV1</name></expr> }</block></expr>,
<expr><block>{ <expr><name>VLC_CODEC_WMA2</name></expr>, <expr><name>AV_CODEC_ID_WMAV2</name></expr> }</block></expr>,
<expr><block>{ <expr><name>VLC_CODEC_MACE3</name></expr>, <expr><name>AV_CODEC_ID_MACE3</name></expr> }</block></expr>,
<expr><block>{ <expr><name>VLC_CODEC_MACE6</name></expr>, <expr><name>AV_CODEC_ID_MACE6</name></expr> }</block></expr>,
<expr><block>{ <expr><name>VLC_CODEC_VMDAUDIO</name></expr>, <expr><name>AV_CODEC_ID_VMDAUDIO</name></expr> }</block></expr>,
<expr><block>{ <expr><name>VLC_CODEC_FLAC</name></expr>, <expr><name>AV_CODEC_ID_FLAC</name></expr> }</block></expr>,


<expr><block>{ <expr><name>VLC_CODEC_SHORTEN</name></expr>, <expr><name>AV_CODEC_ID_SHORTEN</name></expr> }</block></expr>,
<expr><block>{ <expr><name>VLC_CODEC_ALAC</name></expr>, <expr><name>AV_CODEC_ID_ALAC</name></expr> }</block></expr>,

<expr><block>{ <expr><name>VLC_CODEC_GSM</name></expr>, <expr><name>AV_CODEC_ID_GSM</name></expr> }</block></expr>,
<expr><block>{ <expr><name>VLC_CODEC_QDM2</name></expr>, <expr><name>AV_CODEC_ID_QDM2</name></expr> }</block></expr>,
<cpp:if>#<cpp:directive>if</cpp:directive> <expr><operator>(</operator><name>LIBAVCODEC_VERSION_MICRO</name> <operator>&gt;=</operator> <literal type="number">100</literal><operator>)</operator> <operator>&amp;&amp;</operator> <operator>(</operator><name>LIBAVCODEC_VERSION_INT</name> <operator>&gt;=</operator> <call><name>AV_VERSION_INT</name><argument_list>(<argument><expr><literal type="number">57</literal><operator>,</operator> <literal type="number">71</literal><operator>,</operator> <literal type="number">100</literal></expr></argument>)</argument_list></call><operator>)</operator></expr></cpp:if>
<expr><block>{ <expr><name>VLC_CODEC_QDMC</name></expr>, <expr><name>AV_CODEC_ID_QDMC</name></expr> }</block></expr>,
<cpp:endif>#<cpp:directive>endif</cpp:directive></cpp:endif>
<expr><block>{ <expr><name>VLC_CODEC_COOK</name></expr>, <expr><name>AV_CODEC_ID_COOK</name></expr> }</block></expr>,
<expr><block>{ <expr><name>VLC_CODEC_TRUESPEECH</name></expr>, <expr><name>AV_CODEC_ID_TRUESPEECH</name></expr> }</block></expr>,
<expr><block>{ <expr><name>VLC_CODEC_TTA</name></expr>, <expr><name>AV_CODEC_ID_TTA</name></expr> }</block></expr>,
<expr><block>{ <expr><name>VLC_CODEC_SMACKAUDIO</name></expr>, <expr><name>AV_CODEC_ID_SMACKAUDIO</name></expr> }</block></expr>,
<expr><block>{ <expr><name>VLC_CODEC_QCELP</name></expr>, <expr><name>AV_CODEC_ID_QCELP</name></expr> }</block></expr>,
<expr><block>{ <expr><name>VLC_CODEC_WAVPACK</name></expr>, <expr><name>AV_CODEC_ID_WAVPACK</name></expr> }</block></expr>,
<expr><block>{ <expr><name>VLC_CODEC_DSICINAUDIO</name></expr>, <expr><name>AV_CODEC_ID_DSICINAUDIO</name></expr> }</block></expr>,
<expr><block>{ <expr><name>VLC_CODEC_IMC</name></expr>, <expr><name>AV_CODEC_ID_IMC</name></expr> }</block></expr>,
<expr><block>{ <expr><name>VLC_CODEC_MUSEPACK7</name></expr>, <expr><name>AV_CODEC_ID_MUSEPACK7</name></expr> }</block></expr>,
<expr><block>{ <expr><name>VLC_CODEC_MLP</name></expr>, <expr><name>AV_CODEC_ID_MLP</name></expr> }</block></expr>,
<expr><block>{ <expr><name>VLC_CODEC_GSM_MS</name></expr>, <expr><name>AV_CODEC_ID_GSM_MS</name></expr> }</block></expr>,
<expr><block>{ <expr><name>VLC_CODEC_ATRAC3</name></expr>, <expr><name>AV_CODEC_ID_ATRAC3</name></expr> }</block></expr>,
<expr><block>{ <expr><name>VLC_CODEC_APE</name></expr>, <expr><name>AV_CODEC_ID_APE</name></expr> }</block></expr>,
<expr><block>{ <expr><name>VLC_CODEC_NELLYMOSER</name></expr>, <expr><name>AV_CODEC_ID_NELLYMOSER</name></expr> }</block></expr>,
<expr><block>{ <expr><name>VLC_CODEC_MUSEPACK8</name></expr>, <expr><name>AV_CODEC_ID_MUSEPACK8</name></expr> }</block></expr>,
<expr><block>{ <expr><name>VLC_CODEC_SPEEX</name></expr>, <expr><name>AV_CODEC_ID_SPEEX</name></expr> }</block></expr>,
<expr><block>{ <expr><name>VLC_CODEC_WMAS</name></expr>, <expr><name>AV_CODEC_ID_WMAVOICE</name></expr> }</block></expr>,
<expr><block>{ <expr><name>VLC_CODEC_WMAP</name></expr>, <expr><name>AV_CODEC_ID_WMAPRO</name></expr> }</block></expr>,
<expr><block>{ <expr><name>VLC_CODEC_WMAL</name></expr>, <expr><name>AV_CODEC_ID_WMALOSSLESS</name></expr> }</block></expr>,
<expr><block>{ <expr><name>VLC_CODEC_ATRAC3P</name></expr>, <expr><name>AV_CODEC_ID_ATRAC3P</name></expr> }</block></expr>,
<expr><block>{ <expr><name>VLC_CODEC_EAC3</name></expr>, <expr><name>AV_CODEC_ID_EAC3</name></expr> }</block></expr>,
<expr><block>{ <expr><name>VLC_CODEC_SIPR</name></expr>, <expr><name>AV_CODEC_ID_SIPR</name></expr> }</block></expr>,

<expr><block>{ <expr><name>VLC_CODEC_TWINVQ</name></expr>, <expr><name>AV_CODEC_ID_TWINVQ</name></expr> }</block></expr>,
<expr><block>{ <expr><name>VLC_CODEC_TRUEHD</name></expr>, <expr><name>AV_CODEC_ID_TRUEHD</name></expr> }</block></expr>,
<expr><block>{ <expr><name>VLC_CODEC_ALS</name></expr>, <expr><name>AV_CODEC_ID_MP4ALS</name></expr> }</block></expr>,
<expr><block>{ <expr><name>VLC_CODEC_ATRAC1</name></expr>, <expr><name>AV_CODEC_ID_ATRAC1</name></expr> }</block></expr>,
<expr><block>{ <expr><name>VLC_CODEC_BINKAUDIO_RDFT</name></expr>, <expr><name>AV_CODEC_ID_BINKAUDIO_RDFT</name></expr> }</block></expr>,
<expr><block>{ <expr><name>VLC_CODEC_BINKAUDIO_DCT</name></expr>, <expr><name>AV_CODEC_ID_BINKAUDIO_DCT</name></expr> }</block></expr>,
<expr><block>{ <expr><name>VLC_CODEC_MP4A</name></expr>, <expr><name>AV_CODEC_ID_AAC_LATM</name></expr> }</block></expr>,


<expr><block>{ <expr><name>VLC_CODEC_G723_1</name></expr>, <expr><name>AV_CODEC_ID_G723_1</name></expr> }</block></expr>,



<expr><block>{ <expr><name>VLC_CODEC_BMVAUDIO</name></expr>, <expr><name>AV_CODEC_ID_BMV_AUDIO</name></expr> }</block></expr>,
<expr><block>{ <expr><name>VLC_CODEC_RALF</name></expr>, <expr><name>AV_CODEC_ID_RALF</name></expr> }</block></expr>,
<expr><block>{ <expr><name>VLC_CODEC_INDEO_AUDIO</name></expr>, <expr><name>AV_CODEC_ID_IAC</name></expr> }</block></expr>,

<expr><block>{ <expr><name>VLC_CODEC_OPUS</name></expr>, <expr><name>AV_CODEC_ID_OPUS</name></expr> }</block></expr>,

<expr><block>{ <expr><name>VLC_CODEC_TAK</name></expr>, <expr><name>AV_CODEC_ID_TAK</name></expr> }</block></expr>,
<expr><block>{ <expr><name>VLC_CODEC_METASOUND</name></expr>, <expr><name>AV_CODEC_ID_METASOUND</name></expr> }</block></expr>,

<expr><block>{ <expr><name>VLC_CODEC_ON2AVC</name></expr>, <expr><name>AV_CODEC_ID_ON2AVC</name></expr> }</block></expr>,


<cpp:if>#<cpp:directive>if</cpp:directive> <expr><name>LIBAVCODEC_VERSION_MICRO</name> <operator>&gt;=</operator> <literal type="number">100</literal></expr></cpp:if>
<expr><block>{ <expr><name>VLC_CODEC_DSD_LSBF</name></expr>, <expr><name>AV_CODEC_ID_DSD_LSBF</name></expr> }</block></expr>,
<expr><block>{ <expr><name>VLC_CODEC_DSD_MSBF</name></expr>, <expr><name>AV_CODEC_ID_DSD_MSBF</name></expr> }</block></expr>,
<expr><block>{ <expr><name>VLC_CODEC_DSD_LSBF_PLANAR</name></expr>, <expr><name>AV_CODEC_ID_DSD_LSBF_PLANAR</name></expr> }</block></expr>,
<expr><block>{ <expr><name>VLC_CODEC_DSD_MSBF_PLANAR</name></expr>, <expr><name>AV_CODEC_ID_DSD_MSBF_PLANAR</name></expr> }</block></expr>,
<cpp:endif>#<cpp:directive>endif</cpp:directive></cpp:endif>







}</block></expr></init></decl>;</decl_stmt>


<decl_stmt><decl><type><specifier>static</specifier> <specifier>const</specifier> <name><name>struct</name> <name>vlc_avcodec_fourcc</name></name></type> <name><name>spu_codecs</name><index>[]</index></name> <init>=
<expr><block>{
<expr><block>{ <expr><name>VLC_CODEC_SPU</name></expr>, <expr><name>AV_CODEC_ID_DVD_SUBTITLE</name></expr> }</block></expr>,
<expr><block>{ <expr><name>VLC_CODEC_DVBS</name></expr>, <expr><name>AV_CODEC_ID_DVB_SUBTITLE</name></expr> }</block></expr>,
<expr><block>{ <expr><name>VLC_CODEC_SUBT</name></expr>, <expr><name>AV_CODEC_ID_TEXT</name></expr> }</block></expr>,
<expr><block>{ <expr><name>VLC_CODEC_XSUB</name></expr>, <expr><name>AV_CODEC_ID_XSUB</name></expr> }</block></expr>,
<expr><block>{ <expr><name>VLC_CODEC_SSA</name></expr>, <expr><name>AV_CODEC_ID_SSA</name></expr> }</block></expr>,
<expr><block>{ <expr><name>VLC_CODEC_TX3G</name></expr>, <expr><name>AV_CODEC_ID_MOV_TEXT</name></expr> }</block></expr>,
<expr><block>{ <expr><name>VLC_CODEC_BD_PG</name></expr>, <expr><name>AV_CODEC_ID_HDMV_PGS_SUBTITLE</name></expr> }</block></expr>,
<cpp:if>#<cpp:directive>if</cpp:directive> <expr><operator>(</operator><name>LIBAVCODEC_VERSION_MICRO</name> <operator>&gt;=</operator> <literal type="number">100</literal><operator>)</operator> <operator>&amp;&amp;</operator> <operator>(</operator><name>LIBAVCODEC_VERSION_INT</name> <operator>&gt;=</operator> <call><name>AV_VERSION_INT</name><argument_list>(<argument><expr><literal type="number">57</literal><operator>,</operator> <literal type="number">71</literal><operator>,</operator> <literal type="number">100</literal></expr></argument>)</argument_list></call><operator>)</operator></expr></cpp:if>
<expr><block>{ <expr><name>VLC_CODEC_BD_TEXT</name></expr>, <expr><name>AV_CODEC_ID_HDMV_TEXT_SUBTITLE</name></expr> }</block></expr>,
<cpp:endif>#<cpp:directive>endif</cpp:directive></cpp:endif>
<expr><block>{ <expr><name>VLC_CODEC_TELETEXT</name></expr>, <expr><name>AV_CODEC_ID_DVB_TELETEXT</name></expr> }</block></expr>,














}</block></expr></init></decl>;</decl_stmt>

<function><type><name>bool</name></type> <name>GetFfmpegCodec</name><parameter_list>( <parameter><decl><type><name><name>enum</name> <name>es_format_category_e</name></name></type> <name>cat</name></decl></parameter>, <parameter><decl><type><name>vlc_fourcc_t</name></type> <name>i_fourcc</name></decl></parameter>,
<parameter><decl><type><name>unsigned</name> <modifier>*</modifier></type><name>pi_ffmpeg_codec</name></decl></parameter>, <parameter><decl><type><specifier>const</specifier> <name>char</name> <modifier>*</modifier><modifier>*</modifier></type><name>ppsz_name</name></decl></parameter> )</parameter_list>
<block>{<block_content>
<decl_stmt><decl><type><specifier>const</specifier> <name><name>struct</name> <name>vlc_avcodec_fourcc</name></name> <modifier>*</modifier></type><name>base</name></decl>;</decl_stmt>
<decl_stmt><decl><type><name>size_t</name></type> <name>count</name></decl>;</decl_stmt>

<switch>switch<condition>( <expr><name>cat</name></expr> )</condition>
<block>{<block_content>
<case>case <expr><name>VIDEO_ES</name></expr>:</case>
<expr_stmt><expr><name>base</name> <operator>=</operator> <name>video_codecs</name></expr>;</expr_stmt>
<expr_stmt><expr><name>count</name> <operator>=</operator> <call><name>ARRAY_SIZE</name><argument_list>(<argument><expr><name>video_codecs</name></expr></argument>)</argument_list></call></expr>;</expr_stmt>
<break>break;</break>
<case>case <expr><name>AUDIO_ES</name></expr>:</case>
<expr_stmt><expr><name>base</name> <operator>=</operator> <name>audio_codecs</name></expr>;</expr_stmt>
<expr_stmt><expr><name>count</name> <operator>=</operator> <call><name>ARRAY_SIZE</name><argument_list>(<argument><expr><name>audio_codecs</name></expr></argument>)</argument_list></call></expr>;</expr_stmt>
<break>break;</break>
<case>case <expr><name>SPU_ES</name></expr>:</case>
<expr_stmt><expr><name>base</name> <operator>=</operator> <name>spu_codecs</name></expr>;</expr_stmt>
<expr_stmt><expr><name>count</name> <operator>=</operator> <call><name>ARRAY_SIZE</name><argument_list>(<argument><expr><name>spu_codecs</name></expr></argument>)</argument_list></call></expr>;</expr_stmt>
<break>break;</break>
<default>default:</default>
<expr_stmt><expr><name>base</name> <operator>=</operator> <name>NULL</name></expr>;</expr_stmt>
<expr_stmt><expr><name>count</name> <operator>=</operator> <literal type="number">0</literal></expr>;</expr_stmt>
</block_content>}</block></switch>

<expr_stmt><expr><name>i_fourcc</name> <operator>=</operator> <call><name>vlc_fourcc_GetCodec</name><argument_list>( <argument><expr><name>cat</name></expr></argument>, <argument><expr><name>i_fourcc</name></expr></argument> )</argument_list></call></expr>;</expr_stmt>

<for>for<control>( <init><decl><type><name>size_t</name></type> <name>i</name> <init>= <expr><literal type="number">0</literal></expr></init></decl>;</init> <condition><expr><name>i</name> <operator>&lt;</operator> <name>count</name></expr>;</condition> <incr><expr><name>i</name><operator>++</operator></expr></incr> )</control>
<block>{<block_content>
<if_stmt><if>if<condition>( <expr><name><name>base</name><index>[<expr><name>i</name></expr>]</index></name><operator>.</operator><name>i_fourcc</name> <operator>==</operator> <name>i_fourcc</name></expr> )</condition>
<block>{<block_content>
<if_stmt><if>if<condition>( <expr><name>pi_ffmpeg_codec</name> <operator>!=</operator> <name>NULL</name></expr> )</condition><block type="pseudo"><block_content>
<expr_stmt><expr><operator>*</operator><name>pi_ffmpeg_codec</name> <operator>=</operator> <name><name>base</name><index>[<expr><name>i</name></expr>]</index></name><operator>.</operator><name>i_codec</name></expr>;</expr_stmt></block_content></block></if></if_stmt>
<if_stmt><if>if<condition>( <expr><name>ppsz_name</name></expr> )</condition><block type="pseudo"><block_content>
<expr_stmt><expr><operator>*</operator><name>ppsz_name</name> <operator>=</operator> <call><name>vlc_fourcc_GetDescription</name><argument_list>( <argument><expr><name>cat</name></expr></argument>, <argument><expr><name>i_fourcc</name></expr></argument> )</argument_list></call></expr>;</expr_stmt></block_content></block></if></if_stmt>
<return>return <expr><name>true</name></expr>;</return>
</block_content>}</block></if></if_stmt>
</block_content>}</block></for>
<return>return <expr><name>false</name></expr>;</return>
</block_content>}</block></function>

<function><type><name>vlc_fourcc_t</name></type> <name>GetVlcFourcc</name><parameter_list>( <parameter><decl><type><name>unsigned</name></type> <name>i_ffmpeg_codec</name></decl></parameter> )</parameter_list>
<block>{<block_content>
<for>for<control>( <init><decl><type><name>size_t</name></type> <name>i</name> <init>= <expr><literal type="number">0</literal></expr></init></decl>;</init> <condition><expr><name>i</name> <operator>&lt;</operator> <call><name>ARRAY_SIZE</name><argument_list>(<argument><expr><name>video_codecs</name></expr></argument>)</argument_list></call></expr>;</condition> <incr><expr><name>i</name><operator>++</operator></expr></incr> )</control>
<block>{<block_content>
<if_stmt><if>if<condition>( <expr><name>i_ffmpeg_codec</name> <operator>==</operator> <name>AV_CODEC_ID_RAWVIDEO</name></expr> )</condition><block type="pseudo"><block_content>
<return>return <expr><name>VLC_CODEC_UNKNOWN</name></expr>;</return></block_content></block></if></if_stmt>
<if_stmt><if>if<condition>( <expr><name><name>video_codecs</name><index>[<expr><name>i</name></expr>]</index></name><operator>.</operator><name>i_codec</name> <operator>==</operator> <name>i_ffmpeg_codec</name></expr> )</condition><block type="pseudo"><block_content>
<return>return <expr><name><name>video_codecs</name><index>[<expr><name>i</name></expr>]</index></name><operator>.</operator><name>i_fourcc</name></expr>;</return></block_content></block></if></if_stmt>
</block_content>}</block></for>
<for>for<control>( <init><decl><type><name>size_t</name></type> <name>i</name> <init>= <expr><literal type="number">0</literal></expr></init></decl>;</init> <condition><expr><name>i</name> <operator>&lt;</operator> <call><name>ARRAY_SIZE</name><argument_list>(<argument><expr><name>audio_codecs</name></expr></argument>)</argument_list></call></expr>;</condition> <incr><expr><name>i</name><operator>++</operator></expr></incr> )</control>
<block>{<block_content>
<if_stmt><if>if<condition>( <expr><name><name>audio_codecs</name><index>[<expr><name>i</name></expr>]</index></name><operator>.</operator><name>i_codec</name> <operator>==</operator> <name>i_ffmpeg_codec</name></expr> )</condition><block type="pseudo"><block_content>
<return>return <expr><name><name>audio_codecs</name><index>[<expr><name>i</name></expr>]</index></name><operator>.</operator><name>i_fourcc</name></expr>;</return></block_content></block></if></if_stmt>
</block_content>}</block></for>
<for>for<control>( <init><decl><type><name>size_t</name></type> <name>i</name> <init>= <expr><literal type="number">0</literal></expr></init></decl>;</init> <condition><expr><name>i</name> <operator>&lt;</operator> <call><name>ARRAY_SIZE</name><argument_list>(<argument><expr><name>spu_codecs</name></expr></argument>)</argument_list></call></expr>;</condition> <incr><expr><name>i</name><operator>++</operator></expr></incr> )</control>
<block>{<block_content>
<if_stmt><if>if<condition>( <expr><name><name>spu_codecs</name><index>[<expr><name>i</name></expr>]</index></name><operator>.</operator><name>i_codec</name> <operator>==</operator> <name>i_ffmpeg_codec</name></expr> )</condition><block type="pseudo"><block_content>
<return>return <expr><name><name>spu_codecs</name><index>[<expr><name>i</name></expr>]</index></name><operator>.</operator><name>i_fourcc</name></expr>;</return></block_content></block></if></if_stmt>
</block_content>}</block></for>
<return>return <expr><name>VLC_CODEC_UNKNOWN</name></expr>;</return>
</block_content>}</block></function>
</unit>
