<?xml version="1.0" encoding="UTF-8" standalone="yes"?>
<unit xmlns="http://www.srcML.org/srcML/src" xmlns:cpp="http://www.srcML.org/srcML/cpp" revision="1.0.0" language="C" filename="D:\Pesquisa\Projects\vlc-analysis\_cppstats_featurelocations\vlc\modules\gui\macosx\windows\video\VLCVideoOutputProvider.h">






















<cpp:empty>#import &lt;Cocoa/Cocoa.h&gt;</cpp:empty>

<cpp:empty>#import &lt;vlc_vout_window.h&gt;</cpp:empty>

@<decl_stmt><decl><type><name>class</name></type> <name>VLCControlsBarCommon</name></decl>;</decl_stmt>
@<decl_stmt><decl><type><name>class</name></type> <name>VLCVideoWindowCommon</name></decl>;</decl_stmt>
@<decl_stmt><decl><type><name>class</name></type> <name>VLCVoutView</name></decl>;</decl_stmt>

<decl_stmt><decl><type><specifier>extern</specifier> <name>NSString</name> <modifier>*</modifier></type><name>VLCWindowShouldUpdateLevel</name></decl>;</decl_stmt>
<decl_stmt><decl><type><specifier>extern</specifier> <name>NSString</name> <modifier>*</modifier></type><name>VLCWindowLevelKey</name></decl>;</decl_stmt>

@<decl_stmt><decl><type><name>interface</name></type> <name>VLCVideoOutputProvider</name> <range>: <expr><name>NSObject</name>

@<macro><name>property</name> <argument_list>(<argument>readonly</argument>, <argument>nonatomic</argument>)</argument_list></macro> <name>NSInteger</name> <name>currentStatusWindowLevel</name></expr></range></decl>;</decl_stmt>

<expr_stmt><expr><operator>-</operator> <operator>(</operator><name>VLCVoutView</name> <operator>*</operator><operator>)</operator><name>setupVoutForWindow</name><operator>:</operator><operator>(</operator><name>vout_window_t</name> <operator>*</operator><operator>)</operator><name>p_wnd</name> <name>withProposedVideoViewPosition</name><operator>:</operator><operator>(</operator><name>NSRect</name><operator>)</operator><name>videoViewPosition</name></expr>;</expr_stmt>
<expr_stmt><expr><operator>-</operator> <operator>(</operator><name>void</name><operator>)</operator><name>removeVoutForDisplay</name><operator>:</operator><operator>(</operator><name>NSValue</name> <operator>*</operator><operator>)</operator><name>o_key</name></expr>;</expr_stmt>
<expr_stmt><expr><operator>-</operator> <operator>(</operator><name>void</name><operator>)</operator><name>setNativeVideoSize</name><operator>:</operator><operator>(</operator><name>NSSize</name><operator>)</operator><name>size</name> <name>forWindow</name><operator>:</operator><operator>(</operator><name>vout_window_t</name> <operator>*</operator><operator>)</operator><name>p_wnd</name></expr>;</expr_stmt>
<expr_stmt><expr><operator>-</operator> <operator>(</operator><name>void</name><operator>)</operator><name>setWindowLevel</name><operator>:</operator><operator>(</operator><name>NSInteger</name><operator>)</operator><name>i_level</name> <name>forWindow</name><operator>:</operator><operator>(</operator><name>vout_window_t</name> <operator>*</operator><operator>)</operator><name>p_wnd</name></expr>;</expr_stmt>
<expr_stmt><expr><operator>-</operator> <operator>(</operator><name>void</name><operator>)</operator><name>setFullscreen</name><operator>:</operator><operator>(</operator><name>int</name><operator>)</operator><name>i_full</name> <name>forWindow</name><operator>:</operator><operator>(</operator><name>vout_window_t</name> <operator>*</operator><operator>)</operator><name>p_wnd</name> <name>withAnimation</name><operator>:</operator><operator>(</operator><name>BOOL</name><operator>)</operator><name>b_animation</name></expr>;</expr_stmt>

<expr_stmt><expr><operator>-</operator> <operator>(</operator><name>void</name><operator>)</operator><name>updateControlsBarsUsingBlock</name><operator>:</operator><operator>(</operator><call><call><name>void</name> <argument_list>(<argument><expr><operator>^</operator></expr></argument>)</argument_list></call><argument_list>(<argument><expr><name>VLCControlsBarCommon</name> <operator>*</operator><name>controlsBar</name></expr></argument>)</argument_list></call><operator>)</operator><name>block</name></expr>;</expr_stmt>
<expr_stmt><expr><operator>-</operator> <operator>(</operator><name>void</name><operator>)</operator><name>updateWindowsUsingBlock</name><operator>:</operator><operator>(</operator><call><call><name>void</name> <argument_list>(<argument><expr><operator>^</operator></expr></argument>)</argument_list></call><argument_list>(<argument><expr><name>VLCVideoWindowCommon</name> <operator>*</operator><name>o_window</name></expr></argument>)</argument_list></call><operator>)</operator><name>windowUpdater</name></expr>;</expr_stmt>

<expr_stmt><expr><operator>-</operator> <operator>(</operator><name>void</name><operator>)</operator><name>updateWindowLevelForHelperWindows</name><operator>:</operator><operator>(</operator><name>NSInteger</name><operator>)</operator><name>i_level</name></expr>;</expr_stmt>

@<expr><name>end</name></expr>
</unit>
