<?xml version="1.0" encoding="UTF-8" standalone="yes"?>
<unit xmlns="http://www.srcML.org/srcML/src" xmlns:cpp="http://www.srcML.org/srcML/cpp" revision="1.0.0" language="C" filename="D:\Pesquisa\Projects\vlc-analysis\_cppstats\vlc\modules\video_output\wayland\input.h"><cpp:include>#<cpp:directive>include</cpp:directive> <cpp:file>&lt;stdint.h&gt;</cpp:file></cpp:include>

<struct_decl>struct <name>vout_window_t</name>;</struct_decl>

<struct_decl>struct <name>wl_registry</name>;</struct_decl>

<struct_decl>struct <name>wl_surface</name>;</struct_decl>

<struct_decl>struct <name>wl_list</name>;</struct_decl>

<function_decl><type><name>int</name></type> <name>seat_create</name><parameter_list>(<parameter><decl><type><name><name>struct</name> <name>vout_window_t</name></name> <modifier>*</modifier></type><name>wnd</name></decl></parameter>, <parameter><decl><type><name><name>struct</name> <name>wl_registry</name></name> <modifier>*</modifier></type></decl></parameter>,

<parameter><decl><type><name>uint32_t</name></type> <name>name</name></decl></parameter>, <parameter><decl><type><name>uint32_t</name></type> <name>version</name></decl></parameter>, <parameter><decl><type><name><name>struct</name> <name>wl_list</name></name> <modifier>*</modifier></type><name>list</name></decl></parameter>)</parameter_list>;</function_decl>

<function_decl><type><name>int</name></type> <name>seat_destroy_one</name><parameter_list>(<parameter><decl><type><name><name>struct</name> <name>wl_list</name></name> <modifier>*</modifier></type><name>list</name></decl></parameter>, <parameter><decl><type><name>uint32_t</name></type> <name>name</name></decl></parameter>)</parameter_list>;</function_decl>

<function_decl><type><name>void</name></type> <name>seat_destroy_all</name><parameter_list>(<parameter><decl><type><name><name>struct</name> <name>wl_list</name></name> <modifier>*</modifier></type><name>list</name></decl></parameter>)</parameter_list>;</function_decl>

<function_decl><type><name>int</name></type> <name>seat_next_timeout</name><parameter_list>(<parameter><decl><type><specifier>const</specifier> <name><name>struct</name> <name>wl_list</name></name> <modifier>*</modifier></type><name>list</name></decl></parameter>)</parameter_list>;</function_decl>

<function_decl><type><name>void</name></type> <name>seat_timeout</name><parameter_list>(<parameter><decl><type><name><name>struct</name> <name>wl_list</name></name> <modifier>*</modifier></type><name>list</name></decl></parameter>)</parameter_list>;</function_decl>

<function_decl><type><name><name>struct</name> <name>wl_surface</name></name> <modifier>*</modifier></type><name>window_get_cursor</name><parameter_list>(<parameter><decl><type><name>vout_window_t</name> <modifier>*</modifier></type><name>wnd</name></decl></parameter>, <parameter><decl><type><name>int32_t</name> <modifier>*</modifier></type><name>hotspot_x</name></decl></parameter>,

<parameter><decl><type><name>int32_t</name> <modifier>*</modifier></type><name>hotspot_y</name></decl></parameter>)</parameter_list>;</function_decl>

</unit>
